shush/__init__.py
shush/__version__.py
shush/muzzle.py
shush/supress.py
shushlog-0.1.1.dist-info/METADATA
shushlog-0.1.1.dist-info/WHEEL
shushlog-0.1.1.dist-info/licenses/LICENSE
shushlog-0.1.1.dist-info/RECORD
