Metadata-Version: 2.1
Name: shushlog
Version: 0.1.1
Summary: Simple logs supressor and filter
Keywords: logging suppress filter
Author-Email: cătălin <catalin@roboces.dev>
License: GPL-3.0-or-later
Classifier: Development Status :: 4 - Beta
Classifier: License :: OSI Approved :: GNU General Public License v3 or later (GPLv3+)
Classifier: Natural Language :: English
Classifier: Operating System :: POSIX :: Linux
Classifier: Programming Language :: Python :: 3.10
Classifier: Programming Language :: Python :: 3.11
Classifier: Topic :: Software Development
Classifier: Topic :: Software Development :: Libraries
Classifier: Topic :: Software Development :: Libraries :: Python Modules
Project-URL: Homepage, https://git.roboces.dev/catalin/shushlog
Project-URL: Repository, https://git.roboces.dev/catalin/shushlog
Project-URL: Documentation, https://git.roboces.dev/catalin/shushlog
Project-URL: Changelog, https://git.roboces.dev/catalin/shushlog
Requires-Python: >=3.10
Provides-Extra: lint
Provides-Extra: test
Provides-Extra: linters
Requires-Dist: black>=23.9.1; extra == "lint"
Requires-Dist: ruff>=0.0.292; extra == "lint"
Requires-Dist: pytest>=7.4.2; extra == "test"
Requires-Dist: anyio[trio]>=4.0.0; extra == "test"
Requires-Dist: pytest-cov>=4.1.0; extra == "test"
Requires-Dist: mypy>=1.5.1; extra == "linters"
Requires-Dist: pyright>=1.1.329; extra == "linters"
